mlpm_client/__init__.py
mlpm_client-1.0.0.11.dist-info/METADATA
mlpm_client-1.0.0.11.dist-info/WHEEL
mlpm_client-1.0.0.11.dist-info/top_level.txt
mlpm_client-1.0.0.11.dist-info/RECORD
